{
  "id": "",
  "name": "",
  "font_family": "iconfont",
  "css_prefix_text": "icon-",
  "description": "",
  "glyphs": [
    {
      "icon_id": "5047127",
      "name": "首页",
      "font_class": "shouye",
      "unicode": "e602",
      "unicode_decimal": 58882
    },
    {
      "icon_id": "6560965",
      "name": "课程",
      "font_class": "kecheng",
      "unicode": "e609",
      "unicode_decimal": 58889
    },
    {
      "icon_id": "40134564",
      "name": "回看@1x",
      "font_class": "a-huikan1x",
      "unicode": "e693",
      "unicode_decimal": 59027
    }
  ]
}
